shub_cli/__init__.py
shub_cli/cli.py
shub_cli/exceptions.py
shub_cli/config/__init__.py
shub_cli/config/display.py
shub_cli/config/shub_config.py
shub_cli/util/__init__.py
shub_cli/util/display.py
shub_cli/util/parse.py
shub_cli/util/scrapinghub.py
shub_cli-2.0.1.dist-info/DESCRIPTION.rst
shub_cli-2.0.1.dist-info/entry_points.txt
shub_cli-2.0.1.dist-info/METADATA
shub_cli-2.0.1.dist-info/metadata.json
shub_cli-2.0.1.dist-info/RECORD
shub_cli-2.0.1.dist-info/top_level.txt
shub_cli-2.0.1.dist-info/WHEEL
