Metadata-Version: 2.0
Name: shub-cli
Version: 2.0.1
Summary: A CLI at your hands to deal with the features of ScrapingHub.
Home-page: https://github.com/victormartinez/shub_cli
Author: Victor Martinez
Author-email: vcrmartinez@gmail.com
License: MIT
Keywords: cli
Platform: UNKNOWN
Classifier: Intended Audience :: Developers
Classifier: Topic :: Utilities
Classifier: License :: Public Domain
Classifier: Natural Language :: English
Classifier: Operating System :: OS Independent
Classifier: Programming Language :: Python :: 2.7
Classifier: Programming Language :: Python :: 3
Classifier: Programming Language :: Python :: 3.2
Classifier: Programming Language :: Python :: 3.3
Classifier: Programming Language :: Python :: 3.4
Classifier: Programming Language :: Python :: 3.5
Requires-Dist: click-repl (==0.1.0)
Requires-Dist: click (==6.6)
Requires-Dist: hubstorage (==0.23.2)
Requires-Dist: prompt-toolkit (==1.0.7)
Requires-Dist: prompt-toolkit (==1.0.7)
Requires-Dist: Pygments (==2.1.3)
Requires-Dist: PyYAML (==3.12)
Requires-Dist: requests (==2.11.1)
Requires-Dist: retrying (==1.3.3)
Requires-Dist: scrapinghub (==1.9.0)
Requires-Dist: shub (==2.4.2)
Requires-Dist: six (==1.10.0)
Requires-Dist: terminaltables (==3.0.0)
Requires-Dist: toolz (==0.8.0)
Requires-Dist: wcwidth (==0.1.7)
